LICENSE
curses_helper/__init__.py
curses_helper/decorator.py
curses_helper/types.py
curses_helper-0.3.2.dist-info/LICENSE
curses_helper-0.3.2.dist-info/METADATA
curses_helper-0.3.2.dist-info/WHEEL
curses_helper-0.3.2.dist-info/RECORD
