Metadata-Version: 2.1
Name: curses-helper
Version: 0.3.2
Summary: Curses helper stuff.
Home-page: https://github.com/taitep/curses_helper
License: GPL-3.0-or-later
Keywords: curses
Author: taitep
Author-email: taitep@taitep.se
Requires-Python: >=3.9,<4.0
Classifier: License :: OSI Approved :: GNU General Public License v3 or later (GPLv3+)
Classifier: Programming Language :: Python :: 3
Classifier: Programming Language :: Python :: 3.9
Classifier: Programming Language :: Python :: 3.10
Classifier: Programming Language :: Python :: 3.11
Classifier: Programming Language :: Python :: 3.12
Classifier: Programming Language :: Python :: 3.13
Project-URL: Repository, https://github.com/taitep/curses_helper
